rtl/compute/mac_unit.sv
//-----------------------------------------------------------------------------
// Module: mac_unit
// Description: Multiply-Accumulate Unit for INT8 operations
//              Performs: output = input * weight + accumulator
//-----------------------------------------------------------------------------

module mac_unit #(
    parameter int INPUT_WIDTH  = 8,
    parameter int WEIGHT_WIDTH = 8,
    parameter int OUTPUT_WIDTH = 32
)(
    input  logic                      clk,
    input  logic                      rst_n,

    // Control signals
    input  logic                      enable,
    input  logic                      clear_acc,   // Clear accumulator

    // Data inputs
    input  logic [INPUT_WIDTH-1:0]    data_in,     // Input activation
    input  logic [WEIGHT_WIDTH-1:0]   weight_in,   // Weight value

    // Data output
    output logic [OUTPUT_WIDTH-1:0]   data_out     // Accumulated result
);

    //-------------------------------------------------------------------------
    // Internal Signals
    //-------------------------------------------------------------------------
    logic signed [INPUT_WIDTH-1:0]    data_signed;
    logic signed [WEIGHT_WIDTH-1:0]   weight_signed;
    logic signed [INPUT_WIDTH+WEIGHT_WIDTH-1:0] mult_result;
    logic signed [OUTPUT_WIDTH-1:0]   acc_reg;

    //-------------------------------------------------------------------------
    // Sign Extension
    //-------------------------------------------------------------------------
    assign data_signed   = $signed(data_in);
    assign weight_signed = $signed(weight_in);

    //-------------------------------------------------------------------------
    // Multiplication
    //-------------------------------------------------------------------------
    assign mult_result = data_signed * weight_signed;

    //-------------------------------------------------------------------------
    // Accumulator Register
    //-------------------------------------------------------------------------
    always_ff @(posedge clk or negedge rst_n) begin
        if (!rst_n) begin
            acc_reg <= '0;
        end else if (clear_acc) begin
            acc_reg <= '0;
        end else if (enable) begin
            acc_reg <= acc_reg + OUTPUT_WIDTH'(mult_result);
        end
    end

    //-------------------------------------------------------------------------
    // Output Assignment
    //-------------------------------------------------------------------------
    assign data_out = acc_reg;

endmodule

tb/mac_unit_tb.sv
`timescale 1ns/1ps
//-----------------------------------------------------------------------------
// Testbench: mac_unit_tb
// Description: MAC Unit verification with C reference comparison
//              Loads test data via $readmemh and compares results
//              For Vivado simulation
//-----------------------------------------------------------------------------

module mac_unit_tb;

    //-------------------------------------------------------------------------
    // Parameters
    //-------------------------------------------------------------------------
    parameter int INPUT_WIDTH  = 8;
    parameter int WEIGHT_WIDTH = 8;
    parameter int OUTPUT_WIDTH = 32;
    parameter int CLK_PERIOD   = 10;
    parameter int NUM_OPS      = 289;

    // Test data path (update this path for your environment)
    parameter string DATA_PATH = "/home/yc/idsl_npu/sw/ref/";

    //-------------------------------------------------------------------------
    // DUT Signals
    //-------------------------------------------------------------------------
    logic                      clk;
    logic                      rst_n;
    logic                      enable;
    logic                      clear_acc;
    logic signed [INPUT_WIDTH-1:0]    data_in;
    logic signed [WEIGHT_WIDTH-1:0]   weight_in;
    logic signed [OUTPUT_WIDTH-1:0]   data_out;

    //-------------------------------------------------------------------------
    // Reference Data Memory
    //-------------------------------------------------------------------------
    logic [INPUT_WIDTH-1:0]  ref_input    [0:NUM_OPS-1];
    logic [WEIGHT_WIDTH-1:0] ref_weight   [0:NUM_OPS-1];
    logic [7:0]              ref_clear    [0:NUM_OPS-1];
    logic [OUTPUT_WIDTH-1:0] ref_expected [0:NUM_OPS-1];

    //-------------------------------------------------------------------------
    // Test Variables
    //-------------------------------------------------------------------------
    int test_count;
    int pass_count;
    int fail_count;

    //-------------------------------------------------------------------------
    // DUT Instance
    //-------------------------------------------------------------------------
    mac_unit #(
        .INPUT_WIDTH  (INPUT_WIDTH),
        .WEIGHT_WIDTH (WEIGHT_WIDTH),
        .OUTPUT_WIDTH (OUTPUT_WIDTH)
    ) dut (
        .clk        (clk),
        .rst_n      (rst_n),
        .enable     (enable),
        .clear_acc  (clear_acc),
        .data_in    (data_in),
        .weight_in  (weight_in),
        .data_out   (data_out)
    );

    //-------------------------------------------------------------------------
    // Clock Generation
    //-------------------------------------------------------------------------
    initial begin
        clk = 0;
        forever #(CLK_PERIOD/2) clk = ~clk;
    end

    //-------------------------------------------------------------------------
    // Test Tasks
    //-------------------------------------------------------------------------

    // Initialize signals (blocking OK for initial values)
    task automatic init_signals();
        rst_n     = 0;
        enable    = 0;
        clear_acc = 0;
        data_in   = 0;
        weight_in = 0;
        test_count = 0;
        pass_count = 0;
        fail_count = 0;
    endtask

    // Reset sequence
    task automatic do_reset();
        @(posedge clk);
        rst_n <= 0;
        repeat(5) @(posedge clk);
        rst_n <= 1;
        repeat(2) @(posedge clk);
    endtask

    // Single MAC operation from reference data
    task automatic do_mac_op(int idx);
        @(posedge clk);
        // Apply clear if flagged
        if (ref_clear[idx]) begin
            clear_acc <= 1;
            enable    <= 0;
            data_in   <= 0;
            weight_in <= 0;
            @(posedge clk);
            clear_acc <= 0;
        end

        // Apply input/weight and enable
        data_in   <= $signed(ref_input[idx]);
        weight_in <= $signed(ref_weight[idx]);
        enable    <= 1;
        @(posedge clk);
        enable    <= 0;
        @(posedge clk);  // Wait for result to propagate
    endtask

    // Check result against reference
    task automatic check_result(int idx);
        test_count++;
        if (data_out === $signed(ref_expected[idx])) begin
            pass_count++;
        end else begin
            fail_count++;
            $display("===========================================================");
            $display("[FAIL] Operation #%0d", idx);
            $display("       Input:    %0d (0x%02X)", $signed(ref_input[idx]), ref_input[idx]);
            $display("       Weight:   %0d (0x%02X)", $signed(ref_weight[idx]), ref_weight[idx]);
            $display("       Clear:    %0d", ref_clear[idx]);
            $display("       Output:   %0d (0x%08X)", data_out, data_out);
            $display("       Expected: %0d (0x%08X)",
                     $signed(ref_expected[idx]), ref_expected[idx]);
            $display("===========================================================");
            $display("");
            $display("!!! SIMULATION STOPPED DUE TO MISMATCH !!!");
            $display("");
            $finish;
        end
    endtask

    //-------------------------------------------------------------------------
    // Load Reference Data
    //-------------------------------------------------------------------------
    task automatic load_test_data();
        $display("  Loading: %smac_test_input.hex", DATA_PATH);
        $readmemh({DATA_PATH, "mac_test_input.hex"},    ref_input);

        $display("  Loading: %smac_test_weight.hex", DATA_PATH);
        $readmemh({DATA_PATH, "mac_test_weight.hex"},   ref_weight);

        $display("  Loading: %smac_test_clear.hex", DATA_PATH);
        $readmemh({DATA_PATH, "mac_test_clear.hex"},    ref_clear);

        $display("  Loading: %smac_test_expected.hex", DATA_PATH);
        $readmemh({DATA_PATH, "mac_test_expected.hex"}, ref_expected);
    endtask

    //-------------------------------------------------------------------------
    // Main Test Sequence
    //-------------------------------------------------------------------------
    initial begin
        $display("");
        $display("=============================================================");
        $display("        MAC Unit Testbench - Vivado Simulation");
        $display("=============================================================");
        $display("  INPUT_WIDTH:  %0d", INPUT_WIDTH);
        $display("  WEIGHT_WIDTH: %0d", WEIGHT_WIDTH);
        $display("  OUTPUT_WIDTH: %0d", OUTPUT_WIDTH);
        $display("  NUM_OPS:      %0d", NUM_OPS);
        $display("  DATA_PATH:    %s", DATA_PATH);
        $display("=============================================================");
        $display("");

        // Initialize
        init_signals();

        // Load reference data from C-generated hex files
        $display("--- Loading C Reference Data ---");
        load_test_data();
        $display("");

        // Reset
        do_reset();

        //=====================================================================
        // Run all MAC operations from reference data
        //=====================================================================
        $display("--- Running %0d MAC Operations ---", NUM_OPS);

        for (int i = 0; i < NUM_OPS; i++) begin
            do_mac_op(i);
            check_result(i);
        end

        //=====================================================================
        // Test Summary
        //=====================================================================
        $display("");
        $display("=============================================================");
        $display("                    TEST SUMMARY");
        $display("=============================================================");
        $display("  Total tests:  %0d", test_count);
        $display("  Passed:       %0d", pass_count);
        $display("  Failed:       %0d", fail_count);
        $display("=============================================================");

        if (fail_count == 0) begin
            $display("");
            $display("  *** ALL TESTS PASSED ***");
            $display("");
        end

        $finish;
    end

    //-------------------------------------------------------------------------
    // Timeout Watchdog
    //-------------------------------------------------------------------------
    initial begin
        #(CLK_PERIOD * 100000);
        $display("");
        $display("!!! SIMULATION TIMEOUT !!!");
        $display("");
        $finish;
    end

    //-------------------------------------------------------------------------
    // Waveform Dump (for Vivado)
    //-------------------------------------------------------------------------
    initial begin
        $dumpfile("mac_unit_tb.vcd");
        $dumpvars(0, mac_unit_tb);
    end

endmodule

npu_vivado/project_1/project_1.sim/sim_1/behav/xsim/mac_unit_tb.vcd
$date
   Tue Feb  3 01:39:01 2026
$end
$version
  2023.1
$end
$timescale
  1ps
$end
$scope module mac_unit_tb $end
$var reg 1 ! clk $end
$var reg 1 " rst_n $end
$var reg 1 # enable $end
$var reg 1 $ clear_acc $end
$var reg 8 % data_in [7:0] $end
$var reg 8 & weight_in [7:0] $end
$var reg 32 ' data_out [31:0] $end
$var reg 32 ( test_count [31:0] $end
$var reg 32 ) pass_count [31:0] $end
$var reg 32 * fail_count [31:0] $end
$scope module dut $end
$var wire 1 + clk $end
$var wire 1 , rst_n $end
$var wire 1 - enable $end
$var wire 1 . clear_acc $end
$var wire 8 / data_in [7:0] $end
$var wire 8 0 weight_in [7:0] $end
$var reg 32 ' data_out [31:0] $end
$var reg 8 1 data_signed [7:0] $end
$var reg 8 2 weight_signed [7:0] $end
$var reg 16 3 mult_result [15:0] $end
$var reg 32 4 acc_reg [31:0] $end
$upscope $end
$scope begin Block193_3 $end
$var reg 32 5 i [31:0] $end
$upscope $end
$scope task init_signals $end
$upscope $end
$scope task do_reset $end
$upscope $end
$scope task do_mac_op $end
$upscope $end
$scope task check_result $end
$upscope $end
$scope task load_test_data $end
$upscope $end
$upscope $end
$enddefinitions $end
#0
$dumpvars
0!
0"
0#
0$
b0 %
b0 &
b0 '
b0 (
b0 )
b0 *
0+
0,
0-
0.
b0 /
b0 0
b0 1
b0 2
b0 3
b0 4
b0 5
$end
#5000
1!
1+
#10000
0!
0+
#15000
1!
1+
#20000
0!
0+
#25000
1!
1+
#30000
0!
0+
#35000
1!
1+
#40000
0!
0+
#45000
1!
1+
#50000
0!
0+
#55000
1!
1"
1+
1,
#60000
0!
0+
#65000
1!
1+
#70000
0!
0+
#75000
1!
1+
#80000
0!
0+
#85000
1!
1$
1+
1.
#90000
0!
0+
#95000
1!
1#
0$
b10 %
b11 &
1+
1-
0.
b10 /
b11 0
b10 1
b11 2
b110 3
#100000
0!
0+
#105000
1!
0#
b110 '
1+
0-
b110 4
#110000
0!
0+
#115000
1!
b1 (
b1 )
1+
b1 5
#120000
0!
0+
#125000
1!
1#
b100 %
b101 &
1+
1-
b100 /
b101 0
b100 1
b101 2
b10100 3
#130000
0!
0+
#135000
1!
0#
b11010 '
1+
0-
b11010 4
#140000
0!
0+
#145000
1!
b10 (
b10 )
1+
b10 5
#150000
0!
0+
#155000
1!
1$
b0 %
b0 &
1+
1.
b0 /
b0 0
b0 1
b0 2
b0 3
#160000
0!
0+
#165000
1!
1#
0$
b11111011 %
b111 &
b0 '
1+
1-
0.
b11111011 /
b111 0
b11111011 1
b111 2
b1111111111011101 3
b0 4
#170000
0!
0+
#175000
1!
0#
b11111111111111111111111111011101 '
1+
0-
b11111111111111111111111111011101 4
#180000
0!
0+
#185000
1!
b11 (
b11 )
1+
b11 5
#190000
0!
0+
#195000
1!
1$
b0 %
b0 &
1+
1.
b0 /
b0 0
b0 1
b0 2
b0 3
#200000
0!
0+
#205000
1!
1#
0$
b11111101 %
b11111100 &
b0 '
1+
1-
0.
b11111101 /
b11111100 0
b11111101 1
b11111100 2
b1100 3
b0 4
#210000
0!
0+
#215000
1!
0#
b1100 '
1+
0-
b1100 4
#220000
0!
0+
#225000
1!
b100 (
b100 )
1+
b100 5
#230000
0!
0+
#235000
1!
1#
b11111011 %
b111 &
1+
1-
b11111011 /
b111 0
b11111011 1
b111 2
b1111111111011101 3
#240000
0!
0+
#245000
1!
0#
b11111111111111111111111111101001 '
1+
0-
b11111111111111111111111111101001 4
#250000
0!
0+
#255000
1!
b101 (
b101 )
1+
b101 5
#260000
0!
0+
#265000
1!
1$
b0 %
b0 &
1+
1.
b0 /
b0 0
b0 1
b0 2
b0 3
#270000
0!
0+
#275000
1!
1#
0$
b110010 &
b0 '
1+
1-
0.
b110010 0
b110010 2
b0 4
#280000
0!
0+
#285000
1!
0#
1+
0-
#290000
0!
0+
#295000
1!
b110 (
b110 )
1+
b110 5
#300000
0!
0+
#305000
1!
1$
b0 &
1+
1.
b0 0
b0 2
#310000
0!
0+
#315000
1!
1#
0$
b110010 %
1+
1-
0.
b110010 /
b110010 1
#320000
0!
0+
#325000
1!
0#
1+
0-
#330000
0!
0+
#335000
1!
b111 (
b111 )
1+
b111 5
#340000
0!
0+
#345000
1!
1$
b0 %
1+
1.
b0 /
b0 1
#350000
0!
0+
#355000
1!
1#
0$
b1111111 %
b1 &
1+
1-
0.
b1111111 /
b1 0
b1111111 1
b1 2
b1111111 3
#360000
0!
0+
#365000
1!
0#
b1111111 '
1+
0-
b1111111 4
#370000
0!
0+
#375000
1!
b1000 (
b1000 )
1+
b1000 5
#380000
0!
0+
#385000
1!
1$
b0 %
b0 &
1+
1.
b0 /
b0 0
b0 1
b0 2
b0 3
#390000
0!
0+
#395000
1!
1#
0$
b1 %
b10000000 &
b0 '
1+
1-
0.
b1 /
b10000000 0
b1 1
b10000000 2
b1111111110000000 3
b0 4
#400000
0!
0+
#405000
1!
0#
b11111111111111111111111110000000 '
1+
0-
b11111111111111111111111110000000 4
#410000
0!
0+
#415000
1!
b1001 (
b1001 )
1+
b1001 5
#420000
0!
0+
#425000
1!
1$
b0 %
b0 &
1+
1.
b0 /
b0 0
b0 1
b0 2
b0 3
#430000
0!
0+
#435000
1!
1#
0$
b1100100 %
b11111111 &
b0 '
1+
1-
0.
b1100100 /
b11111111 0
b1100100 1
b11111111 2
b1111111110011100 3
b0 4
#440000
0!
0+
#445000
1!
0#
b11111111111111111111111110011100 '
1+
0-
b11111111111111111111111110011100 4
#450000
0!
0+
#455000
1!
b1010 (
b1010 )
1+
b1010 5
#460000
0!
0+
#465000
1!
1$
b0 %
b0 &
1+
1.
b0 /
b0 0
b0 1
b0 2
b0 3
#470000
0!
0+
#475000
1!
1#
0$
b1111111 %
b1111111 &
b0 '
1+
1-
0.
b1111111 /
b1111111 0
b1111111 1
b1111111 2
b11111100000001 3
b0 4
#480000
0!
0+
#485000
1!
0#
b11111100000001 '
1+
0-
b11111100000001 4
#490000
0!
0+
#495000
1!
b1011 (
b1011 )
1+
b1011 5
#500000
0!
0+
#505000
1!
1$
b0 %
b0 &
1+
1.
b0 /
b0 0
b0 1
b0 2
b0 3
#510000
0!
0+
#515000
1!
1#
0$
b10000000 %
b10000000 &
b0 '
1+
1-
0.
b10000000 /
b10000000 0
b10000000 1
b10000000 2
b100000000000000 3
b0 4
#520000
0!
0+
#525000
1!
0#
b100000000000000 '
1+
0-
b100000000000000 4
#530000
0!
0+
#535000
1!
b1100 (
b1100 )
1+
b1100 5
#540000
0!
0+
#545000
1!
1$
b0 %
b0 &
1+
1.
b0 /
b0 0
b0 1
b0 2
b0 3
#550000
0!
0+
#555000
1!
1#
0$
b1111111 %
b10000000 &
b0 '
1+
1-
0.
b1111111 /
b10000000 0
b1111111 1
b10000000 2
b1100000010000000 3
b0 4
#560000
0!
0+
#565000
1!
0#
b11111111111111111100000010000000 '
1+
0-
b11111111111111111100000010000000 4
#570000
0!
0+
#575000
1!
b1101 (
b1101 )
1+
b1101 5
#580000
0!
0+
#585000
1!
1$
b0 %
b0 &
1+
1.
b0 /
b0 0
b0 1
b0 2
b0 3
#590000
0!
0+
#595000
1!
1#
0$
b1111111 %
b1111111 &
b0 '
1+
1-
0.
b1111111 /
b1111111 0
b1111111 1
b1111111 2
b11111100000001 3
b0 4
#600000
0!
0+
#605000
1!
0#
b11111100000001 '
1+
0-
b11111100000001 4
#610000
0!
0+
#615000
1!
b1110 (
b1110 )
1+
b1110 5
#620000
0!
0+
#625000
1!
1#
1+
1-
#630000
0!
0+
#635000
1!
0#
b111111000000010 '
1+
0-
b111111000000010 4
#640000
0!
0+
#645000
1!
b1111 (
b1111 )
1+
b1111 5
#650000
0!
0+
#655000
1!
1#
1+
1-
#660000
0!
0+
#665000
1!
0#
b1011110100000011 '
1+
0-
b1011110100000011 4
#670000
0!
0+
#675000
1!
b10000 (
b10000 )
1+
b10000 5
#680000
0!
0+
#685000
1!
1#
1+
1-
#690000
0!
0+
#695000
1!
0#
b1111110000000100 '
1+
0-
b1111110000000100 4
#700000
0!
0+
#705000
1!
b10001 (
b10001 )
1+
b10001 5
#710000
0!
0+
#715000
1!
1#
1+
1-
#720000
0!
0+
#725000
1!
0#
b10011101100000101 '
1+
0-
b10011101100000101 4
#730000
0!
0+
#735000
1!
b10010 (
b10010 )
1+
b10010 5
#740000
0!
0+
#745000
1!
1#
1+
1-
#750000
0!
0+
#755000
1!
0#
b10111101000000110 '
1+
0-
b10111101000000110 4
#760000
0!
0+
#765000
1!
b10011 (
b10011 )
1+
b10011 5
#770000
0!
0+
#775000
1!
1#
1+
1-
#780000
0!
0+
#785000
1!
0#
b11011100100000111 '
1+
0-
b11011100100000111 4
#790000
0!
0+
#795000
1!
b10100 (
b10100 )
1+
b10100 5
#800000
0!
0+
#805000
1!
1#
1+
1-
#810000
0!
0+
#815000
1!
0#
b11111100000001000 '
1+
0-
b11111100000001000 4
#820000
0!
0+
#825000
1!
b10101 (
b10101 )
1+
b10101 5
#830000
0!
0+
#835000
1!
1#
1+
1-
#840000
0!
0+
#845000
1!
0#
b100011011100001001 '
1+
0-
b100011011100001001 4
#850000
0!
0+
#855000
1!
b10110 (
b10110 )
1+
b10110 5
#860000
0!
0+
#865000
1!
1#
1+
1-
#870000
0!
0+
#875000
1!
0#
b100111011000001010 '
1+
0-
b100111011000001010 4
#880000
0!
0+
#885000
1!
b10111 (
b10111 )
1+
b10111 5
#890000
0!
0+
#895000
1!
1#
1+
1-
#900000
0!
0+
#905000
1!
0#
b101011010100001011 '
1+
0-
b101011010100001011 4
#910000
0!
0+
#915000
1!
b11000 (
b11000 )
1+
b11000 5
#920000
0!
0+
#925000
1!
1#
1+
1-
#930000
0!
0+
#935000
1!
0#
b101111010000001100 '
1+
0-
b101111010000001100 4
#940000
0!
0+
#945000
1!
b11001 (
b11001 )
1+
b11001 5
#950000
0!
0+
#955000
1!
1#
1+
1-
#960000
0!
0+
#965000
1!
0#
b110011001100001101 '
1+
0-
b110011001100001101 4
#970000
0!
0+
#975000
1!
b11010 (
b11010 )
1+
b11010 5
#980000
0!
0+
#985000
1!
1#
1+
1-
#990000
0!
0+
#995000
1!
0#
b110111001000001110 '
1+
0-
b110111001000001110 4
#1000000
0!
0+
#1005000
1!
b11011 (
b11011 )
1+
b11011 5
#1010000
0!
0+
#1015000
1!
1#
1+
1-
#1020000
0!
0+
#1025000
1!
0#
b111011000100001111 '
1+
0-
b111011000100001111 4
#1030000
0!
0+
#1035000
1!
b11100 (
b11100 )
1+
b11100 5
#1040000
0!
0+
#1045000
1!
1#
1+
1-
#1050000
0!
0+
#1055000
1!
0#
b111111000000010000 '
1+
0-
b111111000000010000 4
#1060000
0!
0+
#1065000
1!
b11101 (
b11101 )
1+
b11101 5
#1070000
0!
0+
#1075000
1!
1#
1+
1-
#1080000
0!
0+
#1085000
1!
0#
b1000010111100010001 '
1+
0-
b1000010111100010001 4
#1090000
0!
0+
#1095000
1!
b11110 (
b11110 )
1+
b11110 5
#1100000
0!
0+
#1105000
1!
1#
1+
1-
#1110000
0!
0+
#1115000
1!
0#
b1000110111000010010 '
1+
0-
b1000110111000010010 4
#1120000
0!
0+
#1125000
1!
b11111 (
b11111 )
1+
b11111 5
#1130000
0!
0+
#1135000
1!
1#
1+
1-
#1140000
0!
0+
#1145000
1!
0#
b1001010110100010011 '
1+
0-
b1001010110100010011 4
#1150000
0!
0+
#1155000
1!
b100000 (
b100000 )
1+
b100000 5
#1160000
0!
0+
#1165000
1!
1#
1+
1-
#1170000
0!
0+
#1175000
1!
0#
b1001110110000010100 '
1+
0-
b1001110110000010100 4
#1180000
0!
0+
#1185000
1!
b100001 (
b100001 )
1+
b100001 5
#1190000
0!
0+
#1195000
1!
1#
1+
1-
#1200000
0!
0+
#1205000
1!
0#
b1010010101100010101 '
1+
0-
b1010010101100010101 4
#1210000
0!
0+
#1215000
1!
b100010 (
b100010 )
1+
b100010 5
#1220000
0!
0+
#1225000
1!
1#
1+
1-
#1230000
0!
0+
#1235000
1!
0#
b1010110101000010110 '
1+
0-
b1010110101000010110 4
#1240000
0!
0+
#1245000
1!
b100011 (
b100011 )
1+
b100011 5
#1250000
0!
0+
#1255000
1!
1#
1+
1-
#1260000
0!
0+
#1265000
1!
0#
b1011010100100010111 '
1+
0-
b1011010100100010111 4
#1270000
0!
0+
#1275000
1!
b100100 (
b100100 )
1+
b100100 5
#1280000
0!
0+
#1285000
1!
1#
1+
1-
#1290000
0!
0+
#1295000
1!
0#
b1011110100000011000 '
1+
0-
b1011110100000011000 4
#1300000
0!
0+
#1305000
1!
b100101 (
b100101 )
1+
b100101 5
#1310000
0!
0+
#1315000
1!
1#
1+
1-
#1320000
0!
0+
#1325000
1!
0#
b1100010011100011001 '
1+
0-
b1100010011100011001 4
#1330000
0!
0+
#1335000
1!
b100110 (
b100110 )
1+
b100110 5
#1340000
0!
0+
#1345000
1!
1#
1+
1-
#1350000
0!
0+
#1355000
1!
0#
b1100110011000011010 '
1+
0-
b1100110011000011010 4
#1360000
0!
0+
#1365000
1!
b100111 (
b100111 )
1+
b100111 5
#1370000
0!
0+
#1375000
1!
1#
1+
1-
#1380000
0!
0+
#1385000
1!
0#
b1101010010100011011 '
1+
0-
b1101010010100011011 4
#1390000
0!
0+
#1395000
1!
b101000 (
b101000 )
1+
b101000 5
#1400000
0!
0+
#1405000
1!
1#
1+
1-
#1410000
0!
0+
#1415000
1!
0#
b1101110010000011100 '
1+
0-
b1101110010000011100 4
#1420000
0!
0+
#1425000
1!
b101001 (
b101001 )
1+
b101001 5
#1430000
0!
0+
#1435000
1!
1#
1+
1-
#1440000
0!
0+
#1445000
1!
0#
b1110010001100011101 '
1+
0-
b1110010001100011101 4
#1450000
0!
0+
#1455000
1!
b101010 (
b101010 )
1+
b101010 5
#1460000
0!
0+
#1465000
1!
1#
1+
1-
#1470000
0!
0+
#1475000
1!
0#
b1110110001000011110 '
1+
0-
b1110110001000011110 4
#1480000
0!
0+
#1485000
1!
b101011 (
b101011 )
1+
b101011 5
#1490000
0!
0+
#1495000
1!
1#
1+
1-
#1500000
0!
0+
#1505000
1!
0#
b1111010000100011111 '
1+
0-
b1111010000100011111 4
#1510000
0!
0+
#1515000
1!
b101100 (
b101100 )
1+
b101100 5
#1520000
0!
0+
#1525000
1!
1#
1+
1-
#1530000
0!
0+
#1535000
1!
0#
b1111110000000100000 '
1+
0-
b1111110000000100000 4
#1540000
0!
0+
#1545000
1!
b101101 (
b101101 )
1+
b101101 5
#1550000
0!
0+
#1555000
1!
1#
1+
1-
#1560000
0!
0+
#1565000
1!
0#
b10000001111100100001 '
1+
0-
b10000001111100100001 4
#1570000
0!
0+
#1575000
1!
b101110 (
b101110 )
1+
b101110 5
#1580000
0!
0+
#1585000
1!
1#
1+
1-
#1590000
0!
0+
#1595000
1!
0#
b10000101111000100010 '
1+
0-
b10000101111000100010 4
#1600000
0!
0+
#1605000
1!
b101111 (
b101111 )
1+
b101111 5
#1610000
0!
0+
#1615000
1!
1#
1+
1-
#1620000
0!
0+
#1625000
1!
0#
b10001001110100100011 '
1+
0-
b10001001110100100011 4
#1630000
0!
0+
#1635000
1!
b110000 (
b110000 )
1+
b110000 5
#1640000
0!
0+
#1645000
1!
1#
1+
1-
#1650000
0!
0+
#1655000
1!
0#
b10001101110000100100 '
1+
0-
b10001101110000100100 4
#1660000
0!
0+
#1665000
1!
b110001 (
b110001 )
1+
b110001 5
#1670000
0!
0+
#1675000
1!
1#
1+
1-
#1680000
0!
0+
#1685000
1!
0#
b10010001101100100101 '
1+
0-
b10010001101100100101 4
#1690000
0!
0+
#1695000
1!
b110010 (
b110010 )
1+
b110010 5
#1700000
0!
0+
#1705000
1!
1#
1+
1-
#1710000
0!
0+
#1715000
1!
0#
b10010101101000100110 '
1+
0-
b10010101101000100110 4
#1720000
0!
0+
#1725000
1!
b110011 (
b110011 )
1+
b110011 5
#1730000
0!
0+
#1735000
1!
1#
1+
1-
#1740000
0!
0+
#1745000
1!
0#
b10011001100100100111 '
1+
0-
b10011001100100100111 4
#1750000
0!
0+
#1755000
1!
b110100 (
b110100 )
1+
b110100 5
#1760000
0!
0+
#1765000
1!
1#
1+
1-
#1770000
0!
0+
#1775000
1!
0#
b10011101100000101000 '
1+
0-
b10011101100000101000 4
#1780000
0!
0+
#1785000
1!
b110101 (
b110101 )
1+
b110101 5
#1790000
0!
0+
#1795000
1!
1#
1+
1-
#1800000
0!
0+
#1805000
1!
0#
b10100001011100101001 '
1+
0-
b10100001011100101001 4
#1810000
0!
0+
#1815000
1!
b110110 (
b110110 )
1+
b110110 5
#1820000
0!
0+
#1825000
1!
1#
1+
1-
#1830000
0!
0+
#1835000
1!
0#
b10100101011000101010 '
1+
0-
b10100101011000101010 4
#1840000
0!
0+
#1845000
1!
b110111 (
b110111 )
1+
b110111 5
#1850000
0!
0+
#1855000
1!
1#
1+
1-
#1860000
0!
0+
#1865000
1!
0#
b10101001010100101011 '
1+
0-
b10101001010100101011 4
#1870000
0!
0+
#1875000
1!
b111000 (
b111000 )
1+
b111000 5
#1880000
0!
0+
#1885000
1!
1#
1+
1-
#1890000
0!
0+
#1895000
1!
0#
b10101101010000101100 '
1+
0-
b10101101010000101100 4
#1900000
0!
0+
#1905000
1!
b111001 (
b111001 )
1+
b111001 5
#1910000
0!
0+
#1915000
1!
1#
1+
1-
#1920000
0!
0+
#1925000
1!
0#
b10110001001100101101 '
1+
0-
b10110001001100101101 4
#1930000
0!
0+
#1935000
1!
b111010 (
b111010 )
1+
b111010 5
#1940000
0!
0+
#1945000
1!
1#
1+
1-
#1950000
0!
0+
#1955000
1!
0#
b10110101001000101110 '
1+
0-
b10110101001000101110 4
#1960000
0!
0+
#1965000
1!
b111011 (
b111011 )
1+
b111011 5
#1970000
0!
0+
#1975000
1!
1#
1+
1-
#1980000
0!
0+
#1985000
1!
0#
b10111001000100101111 '
1+
0-
b10111001000100101111 4
#1990000
0!
0+
#1995000
1!
b111100 (
b111100 )
1+
b111100 5
#2000000
0!
0+
#2005000
1!
1#
1+
1-
#2010000
0!
0+
#2015000
1!
0#
b10111101000000110000 '
1+
0-
b10111101000000110000 4
#2020000
0!
0+
#2025000
1!
b111101 (
b111101 )
1+
b111101 5
#2030000
0!
0+
#2035000
1!
1#
1+
1-
#2040000
0!
0+
#2045000
1!
0#
b11000000111100110001 '
1+
0-
b11000000111100110001 4
#2050000
0!
0+
#2055000
1!
b111110 (
b111110 )
1+
b111110 5
#2060000
0!
0+
#2065000
1!
1#
1+
1-
#2070000
0!
0+
#2075000
1!
0#
b11000100111000110010 '
1+
0-
b11000100111000110010 4
#2080000
0!
0+
#2085000
1!
b111111 (
b111111 )
1+
b111111 5
#2090000
0!
0+
#2095000
1!
1#
1+
1-
#2100000
0!
0+
#2105000
1!
0#
b11001000110100110011 '
1+
0-
b11001000110100110011 4
#2110000
0!
0+
#2115000
1!
b1000000 (
b1000000 )
1+
b1000000 5
#2120000
0!
0+
#2125000
1!
1#
1+
1-
#2130000
0!
0+
#2135000
1!
0#
b11001100110000110100 '
1+
0-
b11001100110000110100 4
#2140000
0!
0+
#2145000
1!
b1000001 (
b1000001 )
1+
b1000001 5
#2150000
0!
0+
#2155000
1!
1#
1+
1-
#2160000
0!
0+
#2165000
1!
0#
b11010000101100110101 '
1+
0-
b11010000101100110101 4
#2170000
0!
0+
#2175000
1!
b1000010 (
b1000010 )
1+
b1000010 5
#2180000
0!
0+
#2185000
1!
1#
1+
1-
#2190000
0!
0+
#2195000
1!
0#
b11010100101000110110 '
1+
0-
b11010100101000110110 4
#2200000
0!
0+
#2205000
1!
b1000011 (
b1000011 )
1+
b1000011 5
#2210000
0!
0+
#2215000
1!
1#
1+
1-
#2220000
0!
0+
#2225000
1!
0#
b11011000100100110111 '
1+
0-
b11011000100100110111 4
#2230000
0!
0+
#2235000
1!
b1000100 (
b1000100 )
1+
b1000100 5
#2240000
0!
0+
#2245000
1!
1#
1+
1-
#2250000
0!
0+
#2255000
1!
0#
b11011100100000111000 '
1+
0-
b11011100100000111000 4
#2260000
0!
0+
#2265000
1!
b1000101 (
b1000101 )
1+
b1000101 5
#2270000
0!
0+
#2275000
1!
1#
1+
1-
#2280000
0!
0+
#2285000
1!
0#
b11100000011100111001 '
1+
0-
b11100000011100111001 4
#2290000
0!
0+
#2295000
1!
b1000110 (
b1000110 )
1+
b1000110 5
#2300000
0!
0+
#2305000
1!
1#
1+
1-
#2310000
0!
0+
#2315000
1!
0#
b11100100011000111010 '
1+
0-
b11100100011000111010 4
#2320000
0!
0+
#2325000
1!
b1000111 (
b1000111 )
1+
b1000111 5
#2330000
0!
0+
#2335000
1!
1#
1+
1-
#2340000
0!
0+
#2345000
1!
0#
b11101000010100111011 '
1+
0-
b11101000010100111011 4
#2350000
0!
0+
#2355000
1!
b1001000 (
b1001000 )
1+
b1001000 5
#2360000
0!
0+
#2365000
1!
1#
1+
1-
#2370000
0!
0+
#2375000
1!
0#
b11101100010000111100 '
1+
0-
b11101100010000111100 4
#2380000
0!
0+
#2385000
1!
b1001001 (
b1001001 )
1+
b1001001 5
#2390000
0!
0+
#2395000
1!
1#
1+
1-
#2400000
0!
0+
#2405000
1!
0#
b11110000001100111101 '
1+
0-
b11110000001100111101 4
#2410000
0!
0+
#2415000
1!
b1001010 (
b1001010 )
1+
b1001010 5
#2420000
0!
0+
#2425000
1!
1#
1+
1-
#2430000
0!
0+
#2435000
1!
0#
b11110100001000111110 '
1+
0-
b11110100001000111110 4
#2440000
0!
0+
#2445000
1!
b1001011 (
b1001011 )
1+
b1001011 5
#2450000
0!
0+
